datasette_sqlite_xsv/__init__.py
datasette_sqlite_xsv-0.2.1a13.dist-info/METADATA
datasette_sqlite_xsv-0.2.1a13.dist-info/WHEEL
datasette_sqlite_xsv-0.2.1a13.dist-info/entry_points.txt
datasette_sqlite_xsv-0.2.1a13.dist-info/top_level.txt
datasette_sqlite_xsv-0.2.1a13.dist-info/RECORD
